odoo/addons/l10n_br_sale_stock/README.rst
odoo/addons/l10n_br_sale_stock/__init__.py
odoo/addons/l10n_br_sale_stock/__manifest__.py
odoo/addons/l10n_br_sale_stock/demo/l10n_br_sale_stock_demo.xml
odoo/addons/l10n_br_sale_stock/demo/sale_order_demo.xml
odoo/addons/l10n_br_sale_stock/i18n/l10n_br_sale_stock.pot
odoo/addons/l10n_br_sale_stock/i18n/pt_BR.po
odoo/addons/l10n_br_sale_stock/models/__init__.py
odoo/addons/l10n_br_sale_stock/models/sale_order.py
odoo/addons/l10n_br_sale_stock/models/sale_order_line.py
odoo/addons/l10n_br_sale_stock/models/stock_move.py
odoo/addons/l10n_br_sale_stock/models/stock_picking.py
odoo/addons/l10n_br_sale_stock/readme/CONFIGURE.md
odoo/addons/l10n_br_sale_stock/readme/CONTRIBUTORS.md
odoo/addons/l10n_br_sale_stock/readme/CREDITS.md
odoo/addons/l10n_br_sale_stock/readme/DESCRIPTION.md
odoo/addons/l10n_br_sale_stock/readme/HISTORY.md
odoo/addons/l10n_br_sale_stock/readme/INSTALL.md
odoo/addons/l10n_br_sale_stock/readme/ROADMAP.md
odoo/addons/l10n_br_sale_stock/readme/USAGE.md
odoo/addons/l10n_br_sale_stock/static/description/icon.png
odoo/addons/l10n_br_sale_stock/static/description/index.html
odoo/addons/l10n_br_sale_stock/tests/__init__.py
odoo/addons/l10n_br_sale_stock/tests/test_sale_stock.py
odoo/addons/l10n_br_sale_stock/wizards/__init__.py
odoo/addons/l10n_br_sale_stock/wizards/stock_invoice_onshipping.py
odoo_addon_l10n_br_sale_stock-16.0.3.0.0.dist-info/METADATA
odoo_addon_l10n_br_sale_stock-16.0.3.0.0.dist-info/WHEEL
odoo_addon_l10n_br_sale_stock-16.0.3.0.0.dist-info/top_level.txt
odoo_addon_l10n_br_sale_stock-16.0.3.0.0.dist-info/RECORD
