Metadata-Version: 2.1
Name: odoo-addon-l10n_br_sale_stock
Version: 16.0.3.0.0
Requires-Python: >=3.10
Requires-Dist: odoo-addon-l10n_br_sale>=16.0dev,<16.1dev
Requires-Dist: odoo-addon-l10n_br_stock_account>=16.0dev,<16.1dev
Requires-Dist: odoo-addon-sale_stock_picking_invoicing>=16.0dev,<16.1dev
Requires-Dist: odoo>=16.0a,<16.1dev
Summary: Brazilian Localization Sales and Warehouse
Home-page: https://github.com/OCA/l10n-brazil
License: AGPL-3
Author: Akretion, Odoo Community Association (OCA)
Author-email: support@odoo-community.org
Classifier: Programming Language :: Python
Classifier: Framework :: Odoo
Classifier: Framework :: Odoo :: 16.0
Classifier: License :: OSI Approved :: GNU Affero General Public License v3
Classifier: Development Status :: 4 - Beta
